CHANGELOG.txt
LICENSE.txt
MANIFEST.in
README.txt
setup.py
discordNuker/__init__.py
discordNuker.egg-info/PKG-INFO
discordNuker.egg-info/SOURCES.txt
discordNuker.egg-info/dependency_links.txt
discordNuker.egg-info/requires.txt
discordNuker.egg-info/top_level.txt