Metadata-Version: 2.1
Name: discordNuker
Version: 1.0.2
Summary: A Nuke library for discord.py
Home-page: UNKNOWN
Author: DestructiveLone
Author-email: lambo.blac123@gmail.com
License: MIT
Keywords: nuker
Platform: UNKNOWN
Classifier: Development Status :: 5 - Production/Stable
Classifier: Intended Audience :: Education
Classifier: Operating System :: Microsoft :: Windows :: Windows 10
Classifier: License :: OSI Approved :: MIT License
License-File: LICENSE.txt
